thaitextaug/__init__.py
thaitextaug/wordnet.py
thaitextaug/lm/__init__.py
thaitextaug/lm/fasttext.py
thaitextaug/lm/wangchanberta.py
thaitextaug/word2vec/BPEmb_core.py
thaitextaug/word2vec/__init__.py
thaitextaug/word2vec/thai2fit.py
thaitextaug/word2vec/word2vec.py
thaitextaug-0.0.4.dist-info/LICENSE
thaitextaug-0.0.4.dist-info/METADATA
thaitextaug-0.0.4.dist-info/WHEEL
thaitextaug-0.0.4.dist-info/top_level.txt
thaitextaug-0.0.4.dist-info/RECORD
